<?xml version="1.0"?>
<root>
  <OBJECT NAME="PREFATURAMENTOS_SAIDA">
    <METHOD NAME="LiberarConferenciaManual" DESCRIPTION="Liberar Conferencia Manual" VERSION="6" THREADSAFE="1">
      <PARAMS>
        <GROUPS>
          <GROUP/>
        </GROUPS>
        <PARAM NAME="PREFATURAMENTO" FORMAT="N" SIZE="8" FLAGS="16" PROJECTION="0" ORDER="1" FIELDLABEL="Prefaturamento" CTAB="0"/>
      </PARAMS>
      <FIELDS/>
      <ACTIONSCRIPT>#CHECK("SELECT 1 AS N FROM PREFATURAMENTOS WHERE PREFATURAMENTO = :PREFATURAMENTO AND CONFERIDO = TRUE",N>0,"O pr&#233;-faturamento j&#225; est&#225; com o status de conferido !");

UPDATE PREFATURAMENTOS SET CONFERIDO = 'T', DATACONFERIDO = #NOW(), USERCONFERIDO =  'LIB. S/CONF. POR: '|| #USER()
WHERE PREFATURAMENTO = :PREFATURAMENTO;




</ACTIONSCRIPT>
    </METHOD>
  </OBJECT>
</root>