<dbdic.objects.objects>
  <ROW NAME="DCA_FREQUENCIAS_INSPECOES" CREATE_BLANK="FALSE" ORDER="0">
    <FIELDS NAME="FREQUENCIA_INSPECAO" DATATYPE="3"/>
    <FIELDS NAME="FICHA_TECNICA" DATATYPE="3"/>
    <FIELDS NAME="PARTE" DATATYPE="3"/>
    <FIELDS NAME="DIMENSAO" DATATYPE="1" SIZE="50"/>
    <FIELDS NAME="ESPECIFICACAO" DATATYPE="1" SIZE="50"/>
    <FIELDS NAME="FREQ_INSPECAO" DATATYPE="1" SIZE="10"/>
    <FIELDS NAME="FREQ_ANOTACAO" DATATYPE="1" SIZE="10"/>
    <FIELDS NAME="TECNICA_MEDICAO" DATATYPE="1" SIZE="50"/>
    <INDEXES>
      <FIELDS>FREQUENCIA_INSPECAO</FIELDS>
    </INDEXES>
    <INDEXES>
      <FIELDS>FICHA_TECNICA</FIELDS>
    </INDEXES>
  </ROW>
</dbdic.objects.objects>