<?xml version="1.0"?>
<root>
  <OBJECT NAME="ORDENS_SERVICO">
    <METHOD NAME="PermitirEditarFaturamento" DESCRIPTION="Permitir Editar Faturamento" VERSION="13" INTFTYPE="17" THREADSAFE="0">
      <PARAMS>
        <GROUPS>
          <GROUP/>
        </GROUPS>
        <PARAM NAME="ORDEM_SERVICO" FORMAT="N" SIZE="8" PROJECTION="0" FIELDLABEL="Ordem Servico" CTAB="0"/>
      </PARAMS>
      <FIELDS/>
      <ACTIONSCRIPT>#CHECK("SELECT COUNT(ORDEM_SERVICO) AS N FROM SI_ORDENS_SERVICO WHERE ORDEM_SERVICO=:ORDEM_SERVICO AND STATUS IN (1,4)", N=0, "&#201; necess&#225;rio que a Ordem de servi&#231;o esteja 'AG. FATURAMENTO ENTRADA' ou 'AG.FATURAMENTO'.");

UPDATE SI_ORDENS_SERVICO SET PERMITIR_EDITAR_FAT = STATUS
WHERE ORDEM_SERVICO=:ORDEM_SERVICO;


</ACTIONSCRIPT>
    </METHOD>
  </OBJECT>
</root>