<dbdic.objects.objects>
  <ROW NAME="QIX_PAN_ESTOQUE_FILTROS" CREATE_BLANK="FALSE" ORDER="0">
    <FIELDS NAME="PLANEJAMENTO_ESTOQUE_FILTRO" DATATYPE="3">
      <FLAGS> AQ==
</FLAGS>
    </FIELDS>
    <FIELDS NAME="PLANEJAMENTO_ESTOQUE" DATATYPE="3"/>
    <FIELDS NAME="TIPO" DATATYPE="3"/>
    <FIELDS NAME="VALOR" DATATYPE="3"/>
    <INDEXES>
      <FIELDS>PLANEJAMENTO_ESTOQUE_FILTRO</FIELDS>
      <FLAGS> AQ==
</FLAGS>
    </INDEXES>
    <INDEXES>
      <FIELDS>PLANEJAMENTO_ESTOQUE;TIPO;VALOR</FIELDS>
      <FLAGS> BA==
</FLAGS>
    </INDEXES>
    <INDEXES>
      <FIELDS>PLANEJAMENTO_ESTOQUE</FIELDS>
    </INDEXES>
    <INDEXES>
      <FIELDS>PLANEJAMENTO_ESTOQUE;TIPO</FIELDS>
    </INDEXES>
  </ROW>
</dbdic.objects.objects>