<?xml version="1.0"?>
<root>
  <OBJECT NAME="STATUS_WORKFLOW">
    <METHOD NAME="STATUS_WORKFLOW" DESCRIPTION="" VERSION="4" INTFTYPE="10" TRIGGEROF="MILLENIUM.STATUS_WORKFLOW.STATUS_WORKFLOW" TRIGGERTYPE="0" THREADSAFE="0">
      <PARAMS>
        <GROUPS>
          <GROUP/>
        </GROUPS>
        <PARAM NAME="STATUS_WORKFLOW" FORMAT="+" SIZE="8" FLAGS="1024" SOURCEEXPRESSION="status_workflow.status_workflow.STATUS_WORKFLOW" PROJECTION="0" FIELDLABEL="Status Workflow" CTAB="0"/>
        <PARAM NAME="DESCRICAO" SIZE="50" FLAGS="1" SOURCEEXPRESSION="status_workflow.status_workflow.DESCRICAO" PROJECTION="0" ORDER="1" FIELDLABEL="Descricao" CTAB="0"/>
      </PARAMS>
      <FIELDS/>
      <ACTIONSCRIPT></ACTIONSCRIPT>
    </METHOD>
  </OBJECT>
</root>