<?xml version="1.0"?>
<root>
  <OBJECT NAME="PRODUCAO">
    <METHOD NAME="DistibruirLotes" DESCRIPTION="" VERSION="13" THREADSAFE="1">
      <PARAMS>
        <GROUPS>
          <GROUP/>
        </GROUPS>
        <PARAM NAME="PRODUCAO" FORMAT="N" SIZE="8" FLAGS="1" PROJECTION="0" FIELDLABEL="Ordem" CTAB="0"/>
        <PARAM NAME="DISTRIBUICOES" FORMAT="R" FLAGS="1" PROJECTION="0" FIELDLABEL="Lotes" NESTEDNAME="MILLENIUM!MPITBULLJEANS.PRODUCAO.DISTRIBUICAO" CTAB="0"/>
        <PARAM NAME="LOTES_ORIGINAIS" FORMAT="R" FLAGS="1" PROJECTION="0" FIELDLABEL="Lotes" NESTEDNAME="MILLENIUM!MPITBULLJEANS.PRODUCAO.LOTES" CTAB="0"/>
      </PARAMS>
      <FIELDS/>
      <ACTIONSCRIPT>
</ACTIONSCRIPT>
    </METHOD>
  </OBJECT>
</root>